<?xml version="1.0" encoding="utf-8"?>
<rdf:RDF xmlns:rdf="http://www.w3.org/1999/02/22-rdf-syntax-ns#" xmlns:cim="http://iec.ch/TC57/2013/CIM-schema-cim16#" xmlns:entsoe="http://entsoe.eu/CIM/SchemaExtension/3/1#" xmlns:entsoe2="http://entsoe.eu/CIM/SchemaExtension/3/2#" xmlns:md="http://iec.ch/TC57/61970-552/ModelDescription/1#">
  <md:FullModel rdf:about="urn:uuid:09a32678-2212-11eb-a653-74e5f963e191">
    <md:Model.created>2020-11-08T22:33:34.2532092Z</md:Model.created>
    <md:Model.scenarioTime>2020-11-08T23:30:44.0000000Z</md:Model.scenarioTime>
    <md:Model.version>0</md:Model.version>
    <md:Model.description />
    <md:Model.modelingAuthoritySet>http://www.smib_esst1a.com/smib_esst1a</md:Model.modelingAuthoritySet>
    <md:Model.profile>http://entsoe.eu/CIM/SteadyStateHypothesis/1/1</md:Model.profile>
    <md:Model.DependentOn rdf:resource="urn:uuid:09a32677-2212-11eb-a653-74e5f963e191" />
  </md:FullModel>
  <cim:ConformLoad rdf:about="#_09a326c3-2212-11eb-a653-74e5f963e191">
    <cim:EnergyConsumer.p>50</cim:EnergyConsumer.p>
    <cim:EnergyConsumer.q>10</cim:EnergyConsumer.q>
  </cim:ConformLoad>
  <cim:ControlArea rdf:about="#_09a32681-2212-11eb-a653-74e5f963e191">
    <cim:ControlArea.netInterchange>0</cim:ControlArea.netInterchange>
    <cim:ControlArea.pTolerance>0</cim:ControlArea.pTolerance>
  </cim:ControlArea>
  <cim:GeneratingUnit rdf:about="#_09a326c9-2212-11eb-a653-74e5f963e191">
    <cim:GeneratingUnit.normalPF>0</cim:GeneratingUnit.normalPF>
  </cim:GeneratingUnit>
  <cim:GeneratingUnit rdf:about="#_09a326d1-2212-11eb-a653-74e5f963e191">
    <cim:GeneratingUnit.normalPF>1</cim:GeneratingUnit.normalPF>
  </cim:GeneratingUnit>
  <cim:RegulatingControl rdf:about="#_09a326cc-2212-11eb-a653-74e5f963e191">
    <cim:RegulatingControl.discrete>false</cim:RegulatingControl.discrete>
    <cim:RegulatingControl.enabled>true</cim:RegulatingControl.enabled>
    <cim:RegulatingControl.targetDeadband>0</cim:RegulatingControl.targetDeadband>
    <cim:RegulatingControl.targetValue>100</cim:RegulatingControl.targetValue>
    <cim:RegulatingControl.targetValueUnitMultiplier rdf:resource="http://iec.ch/TC57/2013/CIM-schema-cim16#UnitMultiplier.k" />
  </cim:RegulatingControl>
  <cim:RegulatingControl rdf:about="#_09a326d4-2212-11eb-a653-74e5f963e191">
    <cim:RegulatingControl.discrete>false</cim:RegulatingControl.discrete>
    <cim:RegulatingControl.enabled>true</cim:RegulatingControl.enabled>
    <cim:RegulatingControl.targetDeadband>0</cim:RegulatingControl.targetDeadband>
    <cim:RegulatingControl.targetValue>100</cim:RegulatingControl.targetValue>
    <cim:RegulatingControl.targetValueUnitMultiplier rdf:resource="http://iec.ch/TC57/2013/CIM-schema-cim16#UnitMultiplier.k" />
  </cim:RegulatingControl>
  <cim:SynchronousMachine rdf:about="#_09a326cd-2212-11eb-a653-74e5f963e191">
    <cim:SynchronousMachine.operatingMode rdf:resource="http://iec.ch/TC57/2013/CIM-schema-cim16#SynchronousMachineOperatingMode.generator" />
    <cim:SynchronousMachine.referencePriority>0</cim:SynchronousMachine.referencePriority>
    <cim:RotatingMachine.p>-40</cim:RotatingMachine.p>
    <cim:RotatingMachine.q>-10</cim:RotatingMachine.q>
    <cim:RegulatingCondEq.controlEnabled>true</cim:RegulatingCondEq.controlEnabled>
  </cim:SynchronousMachine>
  <cim:SynchronousMachine rdf:about="#_09a326d5-2212-11eb-a653-74e5f963e191">
    <cim:SynchronousMachine.operatingMode rdf:resource="http://iec.ch/TC57/2013/CIM-schema-cim16#SynchronousMachineOperatingMode.generator" />
    <cim:SynchronousMachine.referencePriority>1</cim:SynchronousMachine.referencePriority>
    <cim:RotatingMachine.p>-12</cim:RotatingMachine.p>
    <cim:RotatingMachine.q>-1</cim:RotatingMachine.q>
    <cim:RegulatingCondEq.controlEnabled>true</cim:RegulatingCondEq.controlEnabled>
  </cim:SynchronousMachine>
  <cim:Terminal rdf:about="#_09a3267d-2212-11eb-a653-74e5f963e191">
    <cim:ACDCTerminal.connected>true</cim:ACDCTerminal.connected>
  </cim:Terminal>
  <cim:Terminal rdf:about="#_09a32699-2212-11eb-a653-74e5f963e191">
    <cim:ACDCTerminal.connected>true</cim:ACDCTerminal.connected>
  </cim:Terminal>
  <cim:Terminal rdf:about="#_09a326a7-2212-11eb-a653-74e5f963e191">
    <cim:ACDCTerminal.connected>true</cim:ACDCTerminal.connected>
  </cim:Terminal>
  <cim:Terminal rdf:about="#_09a326b4-2212-11eb-a653-74e5f963e191">
    <cim:ACDCTerminal.connected>true</cim:ACDCTerminal.connected>
  </cim:Terminal>
  <cim:Terminal rdf:about="#_09a326c5-2212-11eb-a653-74e5f963e191">
    <cim:ACDCTerminal.connected>true</cim:ACDCTerminal.connected>
  </cim:Terminal>
  <cim:Terminal rdf:about="#_09a326ce-2212-11eb-a653-74e5f963e191">
    <cim:ACDCTerminal.connected>true</cim:ACDCTerminal.connected>
  </cim:Terminal>
  <cim:Terminal rdf:about="#_09a326d6-2212-11eb-a653-74e5f963e191">
    <cim:ACDCTerminal.connected>true</cim:ACDCTerminal.connected>
  </cim:Terminal>
  <cim:Terminal rdf:about="#_09a326da-2212-11eb-a653-74e5f963e191">
    <cim:ACDCTerminal.connected>true</cim:ACDCTerminal.connected>
  </cim:Terminal>
  <cim:Terminal rdf:about="#_09a326db-2212-11eb-a653-74e5f963e191">
    <cim:ACDCTerminal.connected>true</cim:ACDCTerminal.connected>
  </cim:Terminal>
  <cim:Terminal rdf:about="#_09a326de-2212-11eb-a653-74e5f963e191">
    <cim:ACDCTerminal.connected>true</cim:ACDCTerminal.connected>
  </cim:Terminal>
  <cim:Terminal rdf:about="#_09a326df-2212-11eb-a653-74e5f963e191">
    <cim:ACDCTerminal.connected>true</cim:ACDCTerminal.connected>
  </cim:Terminal>
  <cim:Terminal rdf:about="#_09a326e2-2212-11eb-a653-74e5f963e191">
    <cim:ACDCTerminal.connected>true</cim:ACDCTerminal.connected>
  </cim:Terminal>
  <cim:Terminal rdf:about="#_09a326e3-2212-11eb-a653-74e5f963e191">
    <cim:ACDCTerminal.connected>true</cim:ACDCTerminal.connected>
  </cim:Terminal>
  <cim:Terminal rdf:about="#_09a326e6-2212-11eb-a653-74e5f963e191">
    <cim:ACDCTerminal.connected>true</cim:ACDCTerminal.connected>
  </cim:Terminal>
  <cim:Terminal rdf:about="#_09a326e7-2212-11eb-a653-74e5f963e191">
    <cim:ACDCTerminal.connected>true</cim:ACDCTerminal.connected>
  </cim:Terminal>
</rdf:RDF>